erizo/__init__.py
erizo/_version.py
erizo/function.py
erizo/version.py
erizo/tests/__init__.py
erizo/tests/test_function.py
erizo-0.0.1.dist-info/AUTHORS.md
erizo-0.0.1.dist-info/LICENSE.txt
erizo-0.0.1.dist-info/METADATA
erizo-0.0.1.dist-info/WHEEL
erizo-0.0.1.dist-info/top_level.txt
erizo-0.0.1.dist-info/RECORD
