Metadata-Version: 2.1
Name: erizo
Version: 0.0.1
Summary: Elastic multi-component interpolation of ground displacement
Home-page: https://github.com/fatiando/erizo
Author: The Erizo Developers
Author-email: leouieda@gmail.com
Maintainer: Leonardo Uieda
Maintainer-email: leouieda@gmail.com
License: BSD License
Keywords: geophysics,geodesy,gps
Platform: Any
Classifier: Development Status :: 3 - Alpha
Classifier: Intended Audience :: Science/Research
Classifier: Intended Audience :: Developers
Classifier: Intended Audience :: Education
Classifier: Topic :: Scientific/Engineering
Classifier: Topic :: Software Development :: Libraries
Classifier: Programming Language :: Python :: 3
Classifier: Programming Language :: Python :: 3.6
Classifier: Programming Language :: Python :: 3.7
Classifier: License :: OSI Approved :: BSD License
Requires-Python: >=3.6
Requires-Dist: numpy
